{
  "inscriptionId": "0d35f73c671880aabd2d80ef0922f8100c75e661bf8c20545ca7c1ebb270fc0ei0",
  "inscriptionNumber": 15608,
  "output": "ae207361318c65bf6d9b93fd3f5d37729bf37f60719f68d395846e638bb7b01f:92",
  "contentType": "image/png",
  "type": "nft",
  "collectionId": "minidoges",
  "itemName": "Doginal Mini Doges",
  "itemId": "1023",
  "attributes": {
    "Background": "Blue",
    "Fur": "Red",
    "Body accessory": "Diamond",
    "Mouth": "Smiling",
    "Mouth accessory": "Rick's drool",
    "Eyes": "Doge eyes"
  }
}