{
  "inscriptionId": "5e467bb7f0ba57c49d8cf797e4557d128cfa2ab4d499d02020f67f734b03f185i0",
  "inscriptionNumber": 17291,
  "output": "bc8a1efc8d043a92d1adc39d1cbca5d8c3ad7ebfd9f71e7e2e456da4fb6bed42:1",
  "contentType": "image/png",
  "type": "nft",
  "collectionId": "minidoges",
  "itemName": "Doginal Mini Doges",
  "itemId": "2657",
  "attributes": {
    "Background": "Gold",
    "Fur": "Red",
    "Body accessory": "Black collar",
    "Mouth": "Neutral",
    "Eyes": "Doge eyes",
    "Head": "Straw hat"
  }
}