{
  "inscriptionId": "d83ddb8ac6295ea66b0cb420b569edc2ebb05106c1480b09105f801480e1fdb0i0",
  "inscriptionNumber": 14873,
  "output": "48ee4be334ab195d12953a9e8aca5b6f938a5926fc9056686dd81447a9afa38f:2",
  "contentType": "image/png",
  "type": "nft",
  "collectionId": "minidoges",
  "itemName": "Doginal Mini Doges",
  "itemId": "296",
  "attributes": {
    "Background": "Blue",
    "Fur": "Black n tan",
    "Body accessory": "Blue kimono",
    "Mouth": "Smiling",
    "Eyes": "Doge eyes",
    "Head": "Hat"
  }
}