{
  "listingId": "677e6ef3afea62741a032195",
  "inscriptionId": "91542119769290f4bdc2dfb2208372c4372530169f82f15b8309cb16b5f5660bi0",
  "inscriptionNumber": 18604,
  "output": "6d36b6fdfa7dd924faa7d59ab310c8bc8aaa1fee9326cf3f087c1176f8e6d3d7:1",
  "status": "listed",
  "contentType": "image/png",
  "type": "nft",
  "sellerAddress": "D9uAN5vv7hY5KHHvJpzimXq14AUY9pAFcv",
  "listedAt": "2025-01-08T12:26:27.628Z",
  "price": 97900000000,
  "collectionId": "minidoges",
  "itemName": "Doginal Mini Doges",
  "itemId": "3970",
  "attributes": {
    "Background": "Blue",
    "Fur": "Red",
    "Body accessory": "Brown hoodie",
    "Mouth": "Smiling",
    "Mouth accessory": "Rick's drool",
    "Eyes": "Pirate patch",
    "Head": "Hat"
  }
}