{
  "inscriptionId": "3a5cb856de17569347b244ea4d26e43c36eb18a712b78dba6ac2d46a3fb84931i0",
  "inscriptionNumber": 19309,
  "output": "44e0b58f9cf111ce7f115492d48c414855b6bb9c212fdf3f9bf19133f8529f62:1",
  "contentType": "image/png",
  "type": "nft",
  "collectionId": "minidoges",
  "itemName": "Doginal Mini Doges",
  "itemId": "4675",
  "attributes": {
    "Background": "White",
    "Fur": "Red",
    "Mouth": "Neutral",
    "Mouth accessory": "Blunt",
    "Eyes": "Doge eyes",
    "Head": "Crown"
  }
}