{
  "inscriptionId": "5d69ee9d85d15b6e28bbf9e5bd87cff06f0d3a4726ce7201ce22bb57317e2de2i0",
  "inscriptionNumber": 15069,
  "output": "5cebba528832d32184efe2e84a8c2e78384065f3f90f24d0076c39abacdbb207:31",
  "contentType": "image/png",
  "type": "nft",
  "collectionId": "minidoges",
  "itemName": "Doginal Mini Doges",
  "itemId": "492",
  "attributes": {
    "Background": "White",
    "Fur": "Black n tan",
    "Body accessory": "Dogecoin",
    "Mouth": "Neutral",
    "Mouth accessory": "Teeth",
    "Eyes": "Doge eyes",
    "Head": "Baseball cap red"
  }
}