{
  "inscriptionId": "980b641634e88c29dca2145fb52bbfa341c9a9ba2fc69cd072cc9c3b550728f3i0",
  "inscriptionNumber": 14635,
  "output": "13ff8c7b885c75b768b984af962b7e85a4e6eee4068b1409de825bd9e49c88e6:57",
  "contentType": "image/png",
  "type": "nft",
  "collectionId": "minidoges",
  "itemName": "Doginal Mini Doges",
  "itemId": "58",
  "attributes": {
    "Background": "Blue",
    "Fur": "Black n tan",
    "Body accessory": "Brown hoodie",
    "Mouth": "Smiling",
    "Mouth accessory": "Rick's drool",
    "Eyes": "Doge eyes",
    "Head": "Baseball cap blue rev"
  }
}