{
  "inscriptionId": "027d8a203c3a9fe0b1933c473352b6db65820ab74e4a61b28188f47497d78c22i0",
  "inscriptionNumber": 21104,
  "output": "408df932a8ac3ce608ffd4177e80304f2e0511be049875536c1eef65f9759cbd:12",
  "contentType": "image/png",
  "type": "nft",
  "collectionId": "minidoges",
  "itemName": "Doginal Mini Doges",
  "itemId": "6470",
  "attributes": {
    "Background": "Fire",
    "Fur": "Cream",
    "Body accessory": "Red kimono",
    "Mouth": "Neutral",
    "Mouth accessory": "Tongue out",
    "Eyes": "Doge eyes",
    "Head": "Straw hat"
  }
}