{
  "inscriptionId": "bc25ae5891df16f310c86f1bf0721b74b061ebefe57c46a73207b284069a5f9di0",
  "inscriptionNumber": 21128,
  "output": "3772609122b2e564b8f1d56c3a4e30a616ed496c87df3697591036eca9f3afd7:0",
  "contentType": "image/png",
  "type": "nft",
  "collectionId": "minidoges",
  "itemName": "Doginal Mini Doges",
  "itemId": "6494",
  "attributes": {
    "Background": "Brown",
    "Fur": "Red",
    "Body accessory": "Dogecoin",
    "Mouth": "Neutral",
    "Mouth accessory": "Rick's drool",
    "Eyes": "Doge eyes"
  }
}