{
  "inscriptionId": "ca8886505d8ce4def59f099605ff2aca48e5b4db2f00d39846c9bf7e043ea455i0",
  "inscriptionNumber": 15339,
  "output": "944ad849aa0d8d088bf19d96eb1a630871b08a83c007db119126d8fbf5029e0c:53",
  "contentType": "image/png",
  "type": "nft",
  "collectionId": "minidoges",
  "itemName": "Doginal Mini Doges",
  "itemId": "754",
  "attributes": {
    "Background": "Blue",
    "Fur": "Red",
    "Body accessory": "Necktie",
    "Mouth": "Neutral",
    "Mouth accessory": "Open mouth",
    "Eyes": "Doge eyes",
    "Head": "Baseball cap blue"
  }
}