{
  "inscriptionId": "aad1d8c94808c370c8e76a1e5a5eacd4176e7cb738976dc49d3f8f9d1de4e77ei0",
  "inscriptionNumber": 22516,
  "output": "3e228d4856d85033c620c5075de57fa3475ff5c38f1e792aaf8cbbaa61bee4a9:7",
  "contentType": "image/png",
  "type": "nft",
  "collectionId": "minidoges",
  "itemName": "Doginal Mini Doges",
  "itemId": "7882",
  "attributes": {
    "Background": "Brown",
    "Fur": "Red",
    "Body accessory": "Blue kimono",
    "Mouth": "Smiling",
    "Eyes": "Doge eyes",
    "Head": "White strip hat"
  }
}