{
  "inscriptionId": "bcfc64e617d9af0240d286a7ca68d0849eb8c8d53134d7fff85a6ed7343ccb9bi0",
  "inscriptionNumber": 22632,
  "output": "f79a62ac1f4af8de5169dd52a8570801f8fb3e8365e5ba2a9db1bcf51bf4ae70:1",
  "contentType": "image/png",
  "type": "nft",
  "collectionId": "minidoges",
  "itemName": "Doginal Mini Doges",
  "itemId": "7998",
  "attributes": {
    "Background": "White",
    "Fur": "Cream",
    "Body accessory": "White hoodie",
    "Mouth": "Smiling",
    "Eyes": "Happy eyes",
    "Head": "Miner hat"
  }
}